HISTORY.rst
LICENSE
MANIFEST.in
README.rst
setup.py
collective/__init__.py
collective/__init__.pyc
collective.purge_behaviors.egg-info/PKG-INFO
collective.purge_behaviors.egg-info/SOURCES.txt
collective.purge_behaviors.egg-info/dependency_links.txt
collective.purge_behaviors.egg-info/entry_points.txt
collective.purge_behaviors.egg-info/namespace_packages.txt
collective.purge_behaviors.egg-info/not-zip-safe
collective.purge_behaviors.egg-info/requires.txt
collective.purge_behaviors.egg-info/top_level.txt
collective/purge_behaviors/__init__.py
collective/purge_behaviors/__init__.pyc
collective/purge_behaviors/behaviors.zcml
collective/purge_behaviors/configure.zcml
collective/purge_behaviors/interfaces.py
collective/purge_behaviors/interfaces.pyc
collective/purge_behaviors/purge.py
collective/purge_behaviors/purge.pyc
collective/purge_behaviors/tests/__init__.py
collective/purge_behaviors/tests/__init__.pyc
collective/purge_behaviors/tests/test_behaviors.py
collective/purge_behaviors/tests/test_behaviors.pyc