Metadata-Version: 1.0
Name: collective.purge-behaviors
Version: 0.1
Summary: A set of dexterity behaviors for Plone that are assignable to custom dexterity types for complex system setups
Home-page: https://github.com/collective/collective.purge_behaviors
Author: eleddy
Author-email: elizabeth.leddy@gmail.com
License: BSD
Platform: UNKNOWN
Classifier: Programming Language :: Python
